cepclient/__init__.py
cepclient/cep
cepclient/cep.py
cepclient/exception.py
cepclient-0.8.3.dist-info/AUTHORS
cepclient-0.8.3.dist-info/LICENSE
cepclient-0.8.3.dist-info/METADATA
cepclient-0.8.3.dist-info/WHEEL
cepclient-0.8.3.dist-info/entry_points.txt
cepclient-0.8.3.dist-info/pbr.json
cepclient-0.8.3.dist-info/top_level.txt
cepclient-0.8.3.dist-info/RECORD
