Metadata-Version: 2.1
Name: cepclient
Version: 0.8.3
Summary: Chameleon Experiment Precis
Home-page: https://www.chameleoncloud.org/
Author: Chameleon
Author-email: users@chameleoncloud.org
License: MIT
Platform: UNKNOWN
Classifier: Programming Language :: Python :: 3
Classifier: License :: OSI Approved :: MIT License
Requires-Dist: keystoneauth1
Requires-Dist: prettytable
Requires-Dist: requests
